[
  {
    "question": "1. 在OSI/RM中，提供建立、维护和拆除端到端连接的层是（ ）",
    "options": [
      "A. 物理层",
      "B. 数据链路层",
      "C. 网络层",
      "D. 运输层"
    ],
    "answer": "D"
  },
  {
    "question": "2. 100BASE-F中，通常F指（ ）",
    "options": [
      "A. 粗缆",
      "B. 光纤",
      "C. 细缆",
      "D. 双绞线"
    ],
    "answer": "B"
  },
  {
    "question": "3. 光纤上采用的多路复用技术是（ ）",
    "options": [
      "A. CDM",
      "B. TDM",
      "C. FDM",
      "D. WDM"
    ],
    "answer": "D"
  },
  {
    "question": "4. 连接两个相距300m的100BASE-T的网络，（ ）是最便宜的网络连接设备",
    "options": [
      "A. 集线器",
      "B. 路由器",
      "C. 交换机",
      "D. 网关"
    ],
    "answer": "A"
  },
  {
    "question": "5. CRC-16标准规定的生成多项式G(x)=x16+x15+x2+1，它产生的校验码是（ ）位",
    "options": [
      "A. 32",
      "B. 8",
      "C. 16",
      "D. 4"
    ],
    "answer": "C"
  },
  {
    "question": "6. 简单邮件传输协议SMTP传输邮件时需要使用（ ）协议",
    "options": [
      "A. TCP",
      "B. FTP",
      "C. UDP",
      "D. POP"
    ],
    "answer": "A"
  },
  {
    "question": "7. （ ）的每一个接口都是一个独立的冲突域",
    "options": [
      "A. 交换机",
      "B. 集线器",
      "C. 网桥",
      "D. 路由器"
    ],
    "answer": "D"
  },
  {
    "question": "8. 在数字通信中广泛采用CRC循环冗余码的原因是CRC可以（ ）",
    "options": [
      "A. 检测出多位突发性差错",
      "B. 检测并纠正一位差错",
      "C. 检测出一位差错",
      "D. 检测并纠正多位突发性差错"
    ],
    "answer": "A"
  },
  {
    "question": "9. 超文本传输协议HTTP使用的端口号是（ ）",
    "options": [
      "A. 23",
      "B. 70",
      "C. 80",
      "D. 110"
    ],
    "answer": "C"
  },
  {
    "question": "10. 数据链路层进行的流量控制是指（ ）的流量控制",
    "options": [
      "A. 源端到目的端",
      "B. 源端到源节点",
      "C. 目的节点到目的端",
      "D. 相邻节点"
    ],
    "answer": "D"
  },
  {
    "question": "11. 当一台主机要获取通信目标的MAC地址时，（ ）",
    "options": [
      "A. 单播ARP请求到默认网关",
      "B. 广播发送ARP请求",
      "C. 与对方主机建立TCP连接",
      "D. 转发IP数据报到邻居结点"
    ],
    "answer": "B"
  },
  {
    "question": "12. 数据链路层服务功能不包括（ ）",
    "options": [
      "A. 无连接不确认服务",
      "B. 面向连接不确认服务",
      "C. 无连接确认服务",
      "D. 面向连接确认服务"
    ],
    "answer": "B"
  },
  {
    "question": "13. RIPv2相对于RIPv1来讲的改进是（ ）",
    "options": [
      "A. 广播方式发布路由更新信息",
      "B. 使用SPF算法计算最短路由",
      "C. 采用了可变长子网掩码",
      "D. 使用更复杂的度量计算方式"
    ],
    "answer": "C"
  },
  {
    "question": "14. PPP协议使用同步传输技术传送比特串00101111111111010，经过零比特填充后的比特串是（ ）",
    "options": [
      "A. 0010111110111110010",
      "B. 0010111101111101010",
      "C. 001011111011111010",
      "D. 001011111111110010"
    ],
    "answer": "C"
  },
  {
    "question": "15. 在物理层接口特性中，用于描述完成每种功能的事件发生顺序的是（ ）特性",
    "options": [
      "A. 机械",
      "B. 功能",
      "C. 过程",
      "D. 电气"
    ],
    "answer": "C"
  },
  {
    "question": "16. 在IP数据报传送过程中，若发现生命周期（TTL）字段等于零，则路由器将发出（ ）",
    "options": [
      "A. 超时",
      "B. 目标不可达",
      "C. 源站抑制",
      "D. 路由重定向"
    ],
    "answer": "A"
  },
  {
    "question": "17. 在Ethernet帧中，数据字段的最小长度是（ ）字节",
    "options": [
      "A. 46",
      "B. 18",
      "C. 64",
      "D. 128"
    ],
    "answer": "A"
  },
  {
    "question": "18. 用于解决电子邮件中传输多种文字和附件问题的是（ ）协议",
    "options": [
      "A. MIME",
      "B. SMTP",
      "C. POP3",
      "D. SNMP"
    ],
    "answer": "A"
  },
  {
    "question": "19. 地址192.168.35.0/28中有（ ）个可用的子网，有（ ）台可用的主机",
    "options": [
      "A. 6，64",
      "B. 14，14",
      "C. 14，32",
      "D. 30，64"
    ],
    "answer": "B"
  },
  {
    "question": "20. 若路由器R因为拥塞丢弃IP分组，则此时R向发出该IP分组的源主机发送的ICMP报文件类型是（ ）",
    "options": [
      "A. 路由重定向",
      "B. 目的站不可达",
      "C. 源站抑制",
      "D. 超时"
    ],
    "answer": "C"
  },
  {
    "question": "21. 下列哪一个不是RIP协议的特点（ ）",
    "options": [
      "A. 仅和相邻路由器交换信息",
      "B. 更新过程的收敛时间很短",
      "C. 按固定的时间间隔交换信息",
      "D. 交换的是自己的路由表"
    ],
    "answer": "B"
  },
  {
    "question": "22. IPv6采用（ ）记法",
    "options": [
      "A. 冒号十六进制",
      "B. 冒号十进制",
      "C. 点分十六进制",
      "D. 点分十进制"
    ],
    "answer": "A"
  },
  {
    "question": "23. 网络层的协议不包括（ ）",
    "options": [
      "A. ICMP",
      "B. ARP",
      "C. IGMP",
      "D. RIP"
    ],
    "answer": "B"
  },
  {
    "question": "24. 利用VLSM划分子网将导致实际可分配的IP地址数目（ ）",
    "options": [
      "A. 不变",
      "B. 减少",
      "C. 增加",
      "D. 不能确定"
    ],
    "answer": "B"
  },
  {
    "question": "25. UDP协议的主要特点不包括（ ）",
    "options": [
      "A. 无连接",
      "B. 不可靠",
      "C. 效率优先",
      "D. 字节流传输"
    ],
    "answer": "D"
  },
  {
    "question": "26. 当一个IP分组在两台主机间直接交付时，要求这两台主机具有相同的（ ）",
    "options": [
      "A. IP地址",
      "B. 主机号",
      "C. 物理地址",
      "D. 子网号"
    ],
    "answer": "D"
  },
  {
    "question": "27. 运输层的端口号分为熟知端口号、（ ）和临时端口号",
    "options": [
      "A. 确认端口号",
      "B. 永久端口号",
      "C. 客户端口号",
      "D. 注册端口号"
    ],
    "answer": "D"
  },
  {
    "question": "28. 路由器的作用是（ ）",
    "options": [
      "A. 过滤与转发帧",
      "B. 放大和整形物理信号",
      "C. 路由选择",
      "D. 协议转换"
    ],
    "answer": "C"
  },
  {
    "question": "29. TCP的流量控制使用的是（ ）",
    "options": [
      "A. 固定大小的滑动窗口协议",
      "B. Go-back-N ARQ协议",
      "C. 可变大小的滑动窗口协议",
      "D. 选择重发ARQ协议"
    ],
    "answer": "C"
  },
  {
    "question": "30. 可靠的传输协议中的\"可靠\"是指（ ）",
    "options": [
      "A. 使用面向连接的会话",
      "B. 使用\"尽力而为\"的传输",
      "C. 使用滑动窗口来维持可靠性",
      "D. 使用确认机制来维持可靠性"
    ],
    "answer": "D"
  },
  {
    "question": "31. FTP客户和服务器之间传递文件时，使用的是建立在（ ）之上的（ ）连接",
    "options": [
      "A. TCP 控制",
      "B. UDP 数据",
      "C. UDP 控制",
      "D. TCP 数据"
    ],
    "answer": "D"
  },
  {
    "question": "32. 一个CIDR地址块222.96.100.2/21包含几个C类地址（ ）",
    "options": [
      "A. 2",
      "B. 4",
      "C. 8",
      "D. 16"
    ],
    "answer": "C"
  },
  {
    "question": "33. 解决IP地址耗尽的根本措施是采用（ ）",
    "options": [
      "A. VPN",
      "B. IPv6",
      "C. NAT",
      "D. IPv4"
    ],
    "answer": "B"
  },
  {
    "question": "34. 下列哪一项不是TCP协议的特点：（ ）",
    "options": [
      "A. 面向连接",
      "B. 可靠交付",
      "C. 面向字节流",
      "D. 首部开销小"
    ],
    "answer": "D"
  },
  {
    "question": "35. 对照OSI/RM各层的网络安全服务，在物理层可采用（ ）技术加强通信线路的安全",
    "options": [
      "A. 防火墙",
      "B. 防病毒",
      "C. 防窃听",
      "D. 防抵赖"
    ],
    "answer": "C"
  }
]